{
    "configuration": {
        "scaleFactor": 0.25,
        "nearPointTolerance": 1.0,
        "linePointTolerance": 3.0
    },
    "pathSegments": [
        {
            "start": {"x": 129, "y": 2297.5},
            "end": {"x": 315, "y": 2297.5}
        },
        {
            "start": {"x": 315, "y": 2297.5},
            "end": {"x": 456.5, "y": 2297.5}
        },
        {
            "start": {"x": 315, "y": 2297.5},
            "end": {"x": 315, "y": 2204}
        },
        {
            "start": {"x": 315, "y": 2204},
            "end": {"x": 398, "y": 2204}
        },
        {
            "start": {"x": 398, "y": 2204},
            "end": {"x": 544.5, "y": 2204}
        },
        {
            "start": {"x": 544.5, "y": 2204},
            "end": {"x": 690.5, "y": 2204}
        },
        {
            "start": {"x": 690.5, "y": 2204},
            "end": {"x": 835.5, "y": 2126.5}
        },
        {
            "start": {"x": 835.5, "y": 2126.5},
            "end": {"x": 899.5, "y": 2126.5}
        },
        {
            "start": {"x": 899.5, "y": 2126.5},
            "end": {"x": 899.5, "y": 2234.5}
        },
        {
            "start": {"x": 899.5, "y": 2234.5},
            "end": {"x": 652.5, "y": 2353}
        },
        {
            "start": {"x": 315, "y": 2204},
            "end": {"x": 247.5, "y": 2204}
        },
        {
            "start": {"x": 247.5, "y": 2204},
            "end": {"x": 100.5, "y": 2109.5}
        },
        {
            "start": {"x": 100.5, "y": 1451},
            "end": {"x": 242, "y": 1372.5}
        },
        {
            "start": {"x": 443, "y": 1372.5},
            "end": {"x": 443, "y": 1410}
        },
        {
            "start": {"x": 899.5, "y": 2126.5},
            "end": {"x": 899.5, "y": 1300}
        },
        {
            "start": {"x": 899.5, "y": 1300},
            "end": {"x": 835.5, "y": 1300}
        },
        {
            "start": {"x": 835.5, "y": 1300},
            "end": {"x": 835.5, "y": 1410}
        },
        {
            "start": {"x": 443, "y": 1300},
            "end": {"x": 443, "y": 1372.5}
        },
        {
            "start": {"x": 690.5, "y": 1410},
            "end": {"x": 835.5, "y": 1410}
        },
        {
            "start": {"x": 443, "y": 1410},
            "end": {"x": 544.5, "y": 1410}
        },
        {
            "start": {"x": 544.5, "y": 1410},
            "end": {"x": 690.5, "y": 1410}
        },
        {
            "start": {"x": 835.5, "y": 1713},
            "end": {"x": 835.5, "y": 1865}
        },
        {
            "start": {"x": 100.5, "y": 1865},
            "end": {"x": 100.5, "y": 1713}
        },
        {
            "start": {"x": 835.5, "y": 1410},
            "end": {"x": 835.5, "y": 1561.5}
        },
        {
            "start": {"x": 835.5, "y": 1561.5},
            "end": {"x": 835.5, "y": 1713}
        },
        {
            "start": {"x": 100.5, "y": 1713},
            "end": {"x": 100.5, "y": 1561.5}
        },
        {
            "start": {"x": 100.5, "y": 1561.5},
            "end": {"x": 100.5, "y": 1451}
        },
        {
            "start": {"x": 544.5, "y": 2204},
            "end": {"x": 544.5, "y": 2033}
        },
        {
            "start": {"x": 835.5, "y": 1865},
            "end": {"x": 835.5, "y": 1986.5}
        },
        {
            "start": {"x": 835.5, "y": 1986.5},
            "end": {"x": 835.5, "y": 2126.5}
        },
        {
            "start": {"x": 398, "y": 2204},
            "end": {"x": 398, "y": 2033}
        },
        {
            "start": {"x": 398, "y": 2033},
            "end": {"x": 398, "y": 1865}
        },
        {
            "start": {"x": 544.5, "y": 2033},
            "end": {"x": 398, "y": 2033}
        },
        {
            "start": {"x": 100.5, "y": 2109.5},
            "end": {"x": 100.5, "y": 1990}
        },
        {
            "start": {"x": 100.5, "y": 1990},
            "end": {"x": 100.5, "y": 1865}
        },
        {
            "start": {"x": 247.5, "y": 1865},
            "end": {"x": 100.5, "y": 1865}
        },
        {
            "start": {"x": 398, "y": 1865},
            "end": {"x": 334, "y": 1865}
        },
        {
            "start": {"x": 334, "y": 1865},
            "end": {"x": 247.5, "y": 1865}
        },
        {
            "start": {"x": 334, "y": 1713},
            "end": {"x": 334, "y": 1865}
        },
        {
            "start": {"x": 334, "y": 1713},
            "end": {"x": 242, "y": 1713}
        },
        {
            "start": {"x": 242, "y": 1713},
            "end": {"x": 100.5, "y": 1713}
        },
        {
            "start": {"x": 242, "y": 1372.5},
            "end": {"x": 391.5, "y": 1372.5}
        },
        {
            "start": {"x": 391.5, "y": 1372.5},
            "end": {"x": 443, "y": 1372.5}
        },
        {
            "start": {"x": 391.5, "y": 1713},
            "end": {"x": 334, "y": 1713}
        },
        {
            "start": {"x": 544.5, "y": 2033},
            "end": {"x": 544.5, "y": 1865}
        },
        {
            "start": {"x": 398, "y": 1865},
            "end": {"x": 544.5, "y": 1865}
        },
        {
            "start": {"x": 835.5, "y": 1713},
            "end": {"x": 690.5, "y": 1713}
        },
        {
            "start": {"x": 690.5, "y": 1713},
            "end": {"x": 544.5, "y": 1713}
        },
        {
            "start": {"x": 544.5, "y": 1713},
            "end": {"x": 391.5, "y": 1713}
        },
        {
            "start": {"x": 544.5, "y": 1865},
            "end": {"x": 544.5, "y": 1713}
        },
        {
            "start": {"x": 247.5, "y": 2204},
            "end": {"x": 247.5, "y": 2011.25}
        },
        {
            "start": {"x": 247.5, "y": 2011.25},
            "end": {"x": 247.5, "y": 1865}
        },
        {
            "start": {"x": 398, "y": 2033},
            "end": {"x": 247.5, "y": 2011.25}
        },
        {
            "start": {"x": 247.5, "y": 2011.25},
            "end": {"x": 100.5, "y": 1990}
        },
        {
            "start": {"x": 690.5, "y": 2009.67},
            "end": {"x": 690.5, "y": 2204}
        },
        {
            "start": {"x": 544.5, "y": 2033},
            "end": {"x": 690.5, "y": 2009.67}
        },
        {
            "start": {"x": 690.5, "y": 2009.67},
            "end": {"x": 835.5, "y": 1986.5}
        },
        {
            "start": {"x": 690.5, "y": 1713},
            "end": {"x": 690.5, "y": 1865}
        },
        {
            "start": {"x": 690.5, "y": 1865},
            "end": {"x": 690.5, "y": 2009.67}
        },
        {
            "start": {"x": 544.5, "y": 1865},
            "end": {"x": 690.5, "y": 1865}
        },
        {
            "start": {"x": 690.5, "y": 1865},
            "end": {"x": 835.5, "y": 1865}
        },
        {
            "start": {"x": 242, "y": 1372.5},
            "end": {"x": 242, "y": 1561.5}
        },
        {
            "start": {"x": 242, "y": 1561.5},
            "end": {"x": 242, "y": 1713}
        },
        {
            "start": {"x": 242, "y": 1561.5},
            "end": {"x": 100.5, "y": 1561.5}
        },
        {
            "start": {"x": 835.5, "y": 1561.5},
            "end": {"x": 391.5, "y": 1561.5}
        },
        {
            "start": {"x": 391.5, "y": 1561.5},
            "end": {"x": 242, "y": 1561.5}
        },
        {
            "start": {"x": 391.5, "y": 1372.5},
            "end": {"x": 391.5, "y": 1561.5}
        },
        {
            "start": {"x": 391.5, "y": 1561.5},
            "end": {"x": 391.5, "y": 1713}
        },
        {
            "start": {"x": 544.5, "y": 1713},
            "end": {"x": 544.5, "y": 1561.5}
        },
        {
            "start": {"x": 544.5, "y": 1561.5},
            "end": {"x": 544.5, "y": 1410}
        },
        {
            "start": {"x": 690.5, "y": 1410},
            "end": {"x": 690.5, "y": 1561.5}
        },
        {
            "start": {"x": 690.5, "y": 1561.5},
            "end": {"x": 690.5, "y": 1713}
        },
        {
            "start": {"x": 443, "y": 1300},
            "end": {"x": 443, "y": 1105.5}
        },
        {
            "start": {"x": 835.5, "y": 1300},
            "end": {"x": 774.5, "y": 1300}
        },
        {
            "start": {"x": 774.5, "y": 1300},
            "end": {"x": 443, "y": 1300}
        },
        {
            "start": {"x": 774.5, "y": 1105.5},
            "end": {"x": 774.5, "y": 1300}
        },
        {
            "start": {"x": 369.5, "y": 1105.5},
            "end": {"x": 369.5, "y": 1145.5}
        },
        {
            "start": {"x": 443, "y": 964},
            "end": {"x": 774.5, "y": 964}
        },
        {
            "start": {"x": 774.5, "y": 964},
            "end": {"x": 774.5, "y": 1105.5}
        },
        {
            "start": {"x": 443, "y": 964},
            "end": {"x": 443, "y": 897.5}
        },
        {
            "start": {"x": 443, "y": 897.5},
            "end": {"x": 774.5, "y": 897.5}
        },
        {
            "start": {"x": 774.5, "y": 897.5},
            "end": {"x": 774.5, "y": 964}
        },
        {
            "start": {"x": 369.5, "y": 1105.5},
            "end": {"x": 194.5, "y": 1105.5}
        },
        {
            "start": {"x": 194.5, "y": 1105.5},
            "end": {"x": 194.5, "y": 1000.5}
        },
        {
            "start": {"x": 194.5, "y": 1000.5},
            "end": {"x": 72.5, "y": 1000.5}
        },
        {
            "start": {"x": 443, "y": 1105.5},
            "end": {"x": 443, "y": 1000.5}
        },
        {
            "start": {"x": 443, "y": 1000.5},
            "end": {"x": 443, "y": 964}
        },
        {
            "start": {"x": 194.5, "y": 1000.5},
            "end": {"x": 443, "y": 1000.5}
        },
        {
            "start": {"x": 369.5, "y": 1105.5},
            "end": {"x": 443, "y": 1105.5}
        },
        {
            "start": {"x": 194.5, "y": 1000.5},
            "end": {"x": 194.5, "y": 852}
        },
        {
            "start": {"x": 194.5, "y": 852},
            "end": {"x": 277, "y": 728}
        },
        {
            "start": {"x": 277, "y": 728},
            "end": {"x": 395, "y": 728}
        },
        {
            "start": {"x": 395, "y": 728},
            "end": {"x": 395, "y": 897.5}
        },
        {
            "start": {"x": 395, "y": 897.5},
            "end": {"x": 443, "y": 897.5}
        }
    ],
    "landmarks": [
        {
            "name": "Collab 07",
            "position": {"x": 137, "y": 2298.86}
        },
        {
            "name": "Collab 07A",
            "position": {"x": 403, "y": 2298.86}
        },
        {
            "name": "Desk 1",
            "position": {"x": 737.32, "y": 2075.86}
        },
        {
            "name": "Desk 10",
            "position": {"x": 736.07, "y": 1932.86}
        },
        {
            "name": "Desk 11",
            "position": {"x": 737.031, "y": 1790.86}
        },
        {
            "name": "Desk 12",
            "position": {"x": 589.188, "y": 1807.86}
        },
        {
            "name": "Desk 13",
            "position": {"x": 382, "y": 1788.86}
        },
        {
            "name": "Desk 14",
            "position": {"x": 238.471, "y": 1787.86}
        },
        {
            "name": "Desk 15",
            "position": {"x": 152.17, "y": 1645.86}
        },
        {
            "name": "Desk 16",
            "position": {"x": 294.076, "y": 1622.86}
        },
        {
            "name": "Desk 17",
            "position": {"x": 443.393, "y": 1644.86}
        },
        {
            "name": "Desk 18",
            "position": {"x": 589.123, "y": 1657.86}
        },
        {
            "name": "Desk 19",
            "position": {"x": 728.076, "y": 1643.86}
        },
        {
            "name": "Desk 20",
            "position": {"x": 728.227, "y": 1501.86}
        },
        {
            "name": "Desk 21",
            "position": {"x": 586.188, "y": 1502.86}
        },
        {
            "name": "Desk 22",
            "position": {"x": 444.344, "y": 1501.86}
        },
        {
            "name": "Desk 23",
            "position": {"x": 293.156, "y": 1462.86}
        },
        {
            "name": "Pantry",
            "position": {"x": 599.759, "y": 1114.55}
        },
        {
            "name": "Desk 24",
            "position": {"x": 147.221, "y": 1506.86}
        },
        {
            "name": "Desk 2",
            "position": {"x": 588.477, "y": 2118.86}
        },
        {
            "name": "Desk 9",
            "position": {"x": 598.365, "y": 1959.86}
        },
        {
            "name": "Desk 3",
            "position": {"x": 445.289, "y": 2114.86}
        },
        {
            "name": "Desk 8",
            "position": {"x": 448.412, "y": 1949.86}
        },
        {
            "name": "Desk 4",
            "position": {"x": 294.26, "y": 2118.86}
        },
        {
            "name": "Desk 7",
            "position": {"x": 296.182, "y": 1950.86}
        },
        {
            "name": "Desk 6",
            "position": {"x": 152.365, "y": 1933.86}
        },
        {
            "name": "Desk 5",
            "position": {"x": 152.459, "y": 2077.86}
        },
        {
            "name": "Main Entrance",
            "position": {"x": 618, "y": 2356.86}
        },
        {
            "name": "Side Entrance",
            "position": {"x": 43, "y": 1001.86}
        },
        {
            "name": "Collab 01",
            "position": {"x": 168, "y": 1111.86}
        },
        {
            "name": "Board Room",
            "position": {"x": 327.31, "y": 1167.55}
        },
        {
            "name": "Collab 02",
            "position": {"x": 126, "y": 818.864}
        },
        {
            "name": "Collab 03",
            "position": {"x": 241, "y": 685.864}
        },
        {
            "name": "Collab 03A",
            "position": {"x": 338, "y": 947.864}
        }
    ]
}
